origami/__init__.py
origami_theme-0.1.0.dist-info/entry_points.txt
origami_theme-0.1.0.dist-info/WHEEL
origami_theme-0.1.0.dist-info/METADATA
origami_theme-0.1.0.dist-info/RECORD
