Metadata-Version: 2.1
Name: origami-theme
Version: 0.1.0
Summary: Origami sphinx theme
Author: Bartek Sokorski
Author-email: b.sokorski@gmail.com
Requires-Python: >=3.7,<4.0
Classifier: Programming Language :: Python :: 3
Classifier: Programming Language :: Python :: 3.7
Classifier: Programming Language :: Python :: 3.8
Classifier: Programming Language :: Python :: 3.9
Classifier: Programming Language :: Python :: 3.10
Requires-Dist: Pygments (>=2.12.0,<3.0.0)
Requires-Dist: Sphinx (>=5.0.2,<6.0.0)
Requires-Dist: sphinx-copybutton (>=0.5.0,<0.6.0)
